setup.py
smslogger/__init__.py
smslogger/textlogger.py
smslogger.egg-info/PKG-INFO
smslogger.egg-info/SOURCES.txt
smslogger.egg-info/dependency_links.txt
smslogger.egg-info/not-zip-safe
smslogger.egg-info/top_level.txt