Metadata-Version: 1.0
Name: smslogger
Version: 0.1
Summary: Send important logging events as text messages
Home-page: http://github.com/davefol/smslogger
Author: Dave Fol
Author-email: dof5@cornell.edu
License: GNU
Platform: UNKNOWN
